iotile_support_con_nrf52832_2/__init__.py
iotile_support_con_nrf52832_2/nrf52832_controller.py
iotile_support_con_nrf52832_2-2.15.4.dist-info/METADATA
iotile_support_con_nrf52832_2-2.15.4.dist-info/RECORD
iotile_support_con_nrf52832_2-2.15.4.dist-info/WHEEL
iotile_support_con_nrf52832_2-2.15.4.dist-info/entry_points.txt
iotile_support_con_nrf52832_2-2.15.4.dist-info/top_level.txt
